{
  "code": "#include \"clang/AST/ASTDumperUtils.h\"\n#include \"clang/AST/AttrIterator.h\"\n#include \"clang/AST/DeclarationName.h\"\n#include \"clang/Basic/IdentifierTable.h\"\n#include \"clang/Basic/LLVM.h\"\n#include \"clang/Basic/SourceLocation.h\"\n#include \"clang/Basic/Specifiers.h\"\n#include \"llvm/ADT/ArrayRef.h\"\n#include \"llvm/ADT/PointerIntPair.h\"\n#include \"llvm/ADT/PointerUnion.h\"\n#include \"llvm/ADT/iterator.h\"\n#include \"llvm/ADT/iterator_range.h\"\n#include \"llvm/Support/Casting.h\"\n#include \"llvm/Support/Compiler.h\"\n#include \"llvm/Support/PrettyStackTrace.h\"\n#include \"llvm/Support/VersionTuple.h\"\n#include <algorithm>\n#include <cassert>\n#include <cstddef>\n#include <iterator>\n#include <string>\n#include <type_traits>\n#include <utility>\n#include \"clang/AST/DeclNodes.inc\"\n\nusing namespace clang;\nusing namespace during;\nusing namespace foo;\nusing namespace but;\nusing namespace but;\nusing namespace A;\nusing namespace A;\nusing namespace this;\nusing namespace A;\nusing namespace B;\nusing namespace A;\nusing namespace A;\nusing namespace of;\nusing namespace is;\nusing namespace of;\nusing namespace includes;\nusing namespace includes;\nusing namespace of;\nusing namespace clang;\nusing namespace llvm;\nusing namespace clang;\nusing namespace A;\nusing namespace context;\nusing namespace set;\nusing namespace set;\nusing namespace N;\nusing namespace N;\nusing namespace contexts;\n\nextern \"C\" {\n\nvoid BLOCK-CPP-08297_execute() {\n    { return decl_iterator(FirstDecl); }\n}\n\n} // extern \"C\"\n",
  "id": "BLOCK-CPP-08297",
  "language": "c++",
  "source_file": "/storage/emulated/0/Download/cpp_codebases/llvm/clang/include/clang/AST/DeclBase.h",
  "source_line": 2217,
  "validation_status": "validated"
}