{
  "code": "#include \"clang/AST/APValue.h\"\n#include \"clang/AST/ASTVector.h\"\n#include \"clang/AST/ComputeDependence.h\"\n#include \"clang/AST/Decl.h\"\n#include \"clang/AST/DeclAccessPair.h\"\n#include \"clang/AST/DependenceFlags.h\"\n#include \"clang/AST/OperationKinds.h\"\n#include \"clang/AST/Stmt.h\"\n#include \"clang/AST/TemplateBase.h\"\n#include \"clang/AST/Type.h\"\n#include \"clang/Basic/CharInfo.h\"\n#include \"clang/Basic/LangOptions.h\"\n#include \"clang/Basic/SyncScope.h\"\n#include \"clang/Basic/TypeTraits.h\"\n#include \"llvm/ADT/APFloat.h\"\n#include \"llvm/ADT/APSInt.h\"\n#include \"llvm/ADT/SmallVector.h\"\n#include \"llvm/ADT/StringRef.h\"\n#include \"llvm/ADT/iterator.h\"\n#include \"llvm/ADT/iterator_range.h\"\n#include \"llvm/Support/AtomicOrdering.h\"\n#include \"llvm/Support/Compiler.h\"\n#include \"llvm/Support/TrailingObjects.h\"\n#include <optional>\n\nusing namespace clang;\n\nextern \"C\" {\n\nvoid BLOCK-CPP-10275_execute() {\n    {\n      /// Refers to the field that is being initialized. The low bit\n      /// of this field determines whether this is actually a pointer\n      /// to an IdentifierInfo (if 1) or a FieldDecl (if 0). When\n      /// initially constructed, a field designator will store an\n      /// IdentifierInfo*. After semantic analysis has resolved that\n      /// name, the field designator will instead store a FieldDecl*.\n      uintptr_t NameOrField;\n\n      /// The location of the '.' in the designated initializer.\n      SourceLocation DotLoc;\n\n      /// The location of the field name in the designated initializer.\n      SourceLocation FieldLoc;\n\n      FieldDesignatorInfo(const IdentifierInfo *II, SourceLocation DotLoc,\n                          SourceLocation FieldLoc)\n          : NameOrField(reinterpret_cast<uintptr_t>(II) | 0x1), DotLoc(DotLoc),\n            FieldLoc(FieldLoc) {}\n    }\n}\n\n} // extern \"C\"\n",
  "id": "BLOCK-CPP-10275",
  "language": "c++",
  "source_file": "/storage/emulated/0/Download/cpp_codebases/llvm/clang/include/clang/AST/Expr.h",
  "source_line": 5118,
  "validation_status": "validated"
}