{
  "code": "#include <cassert>\n#include <cstdint>\n#include <cstdio>\n#include <limits>\n#include \"absl/base/config.h\"\n#include \"absl/base/const_init.h\"\n#include \"absl/base/optimization.h\"\n#include \"absl/strings/internal/str_format/extension.h\"\n\nusing namespace absl;\nusing namespace str_format_internal;\n\nextern \"C\" {\n\nvoid BLOCK-CPP-06345_execute() {\n    {\n    assert(!is_conv());\n    assert(!is_length());\n    assert(is_flags());\n    return static_cast<Flags>(tag_ & 0x1F);\n  }\n}\n\n} // extern \"C\"\n",
  "id": "BLOCK-CPP-06345",
  "language": "c++",
  "source_file": "/storage/emulated/0/Download/cpp_codebases/abseil/absl/strings/internal/str_format/constexpr_parser.h",
  "source_line": 110,
  "validation_status": "validated"
}