{
  "code": "{\n public:\n  using result_type = RealType;\n\n  class param_type {\n   public:\n    using distribution_type = uniform_real_distribution;\n\n    explicit param_type(result_type lo = 0, result_type hi = 1)\n        : lo_(lo), hi_(hi), range_(hi - lo) {\n      // [rand.dist.uni.real] preconditions 2 & 3\n      assert(lo <= hi);\n\n      // NOTE: For integral types, we can promote the range to an unsigned type,\n      // which gives full width of the range. However for real (fp) types, this\n      // is not possible, so value generation cannot use the full range of the\n      // real type.\n      assert(range_ <= (std::numeric_limits<result_type>::max)());\n    }\n\n    result_type a() const { return lo_; }\n    result_type b() const { return hi_; }\n\n    friend bool operator==(const param_type& a, const param_type& b) {\n      return a.lo_ == b.lo_ && a.hi_ == b.hi_;\n    }\n\n    friend bool operator!=(const param_type& a, const param_type& b) {\n      return !(a == b);\n    }\n\n   private:\n    friend class uniform_real_distribution;\n    result_type lo_, hi_, range_;\n\n    static_assert(std::is_floating_point<RealType>::value,\n                  \"Class-template absl::uniform_real_distribution<> must be \"\n                  \"parameterized using a floating-point type.\");\n  };\n\n  uniform_real_distribution() : uniform_real_distribution(0) {}\n\n  explicit uniform_real_distribution(result_type lo, result_type hi = 1)\n      : param_(lo, hi) {}\n\n  explicit uniform_real_distribution(const param_type& param) : param_(param) {}\n\n  // uniform_real_distribution<T>::reset()\n  //\n  // Resets the uniform real distribution. Note that this function has no effect\n  // because the distribution already produces independent values.\n  void reset() {}\n\n  template <typename URBG>\n  result_type operator()(URBG& gen) {  // NOLINT(runtime/references)\n    return operator()(gen, param_);\n  }\n\n  template <typename URBG>\n  result_type operator()(URBG& gen,  // NOLINT(runtime/references)\n                         const param_type& p);\n\n  result_type a() const { return param_.a(); }\n  result_type b() const { return param_.b(); }\n\n  param_type param() const { return param_; }\n  void param(const param_type& params) { param_ = params; }\n\n  result_type(min)() const { return a(); }\n  result_type(max)() const { return b(); }\n\n  friend bool operator==(const uniform_real_distribution& a,\n                         const uniform_real_distribution& b) {\n    return a.param_ == b.param_;\n  }\n  friend bool operator!=(const uniform_real_distribution& a,\n                         const uniform_real_distribution& b) {\n    return a.param_ != b.param_;\n  }\n\n private:\n  param_type param_;\n  random_internal::FastUniformBits<uint64_t> fast_u64_;\n}",
  "id": "BLOCK-CPP-03923",
  "language": "c++",
  "source_file": "/storage/emulated/0/Download/cpp_codebases/abseil/absl/random/uniform_real_distribution.h",
  "source_line": 63,
  "validation_status": "validated"
}