{
  "code": "#include \"clang/AST/Stmt.h\"\n#include \"clang/Analysis/AnalysisDeclContext.h\"\n#include \"clang/Basic/LLVM.h\"\n#include \"clang/Basic/SourceLocation.h\"\n#include \"llvm/ADT/ArrayRef.h\"\n#include \"llvm/ADT/FoldingSet.h\"\n#include \"llvm/ADT/PointerUnion.h\"\n#include \"llvm/ADT/SmallVector.h\"\n#include \"llvm/ADT/StringRef.h\"\n#include \"llvm/Support/Allocator.h\"\n#include <cassert>\n#include <deque>\n#include <iterator>\n#include <list>\n#include <map>\n#include <memory>\n#include <optional>\n#include <set>\n#include <string>\n#include <utility>\n#include <vector>\n\nusing namespace clang;\nusing namespace ento;\n\nextern \"C\" {\n\nvoid BLOCK-CPP-15796_execute() {\n    {\n  /// Run-line of the tool that produced the diagnostic.\n  /// It can be included with the diagnostic for debugging purposes.\n  std::string ToolInvocation;\n\n  /// Whether to include additional information about macro expansions\n  /// with the diagnostics, because otherwise they can be hard to obtain\n  /// without re-compiling the program under analysis.\n  bool ShouldDisplayMacroExpansions = false;\n\n  /// Whether to include LLVM statistics of the process in the diagnostic.\n  /// Useful for profiling the tool on large real-world codebases.\n  bool ShouldSerializeStats = false;\n\n  /// If the consumer intends to produce multiple output files, should it\n  /// use a pseudo-random file name or a human-readable file name.\n  bool ShouldWriteVerboseReportFilename = false;\n\n  /// Whether the consumer should treat consumed diagnostics as hard errors.\n  /// Useful for breaking your build when issues are found.\n  bool ShouldDisplayWarningsAsErrors = false;\n\n  /// Whether the consumer should attempt to rewrite the source file\n  /// with fix-it hints attached to the diagnostics it consumes.\n  bool ShouldApplyFixIts = false;\n\n  /// Whether the consumer should present the name of the entity that emitted\n  /// the diagnostic (eg., a checker) so that the user knew how to disable it.\n  bool ShouldDisplayDiagnosticName = false;\n}\n}\n\n} // extern \"C\"\n",
  "id": "BLOCK-CPP-15796",
  "language": "c++",
  "source_file": "/storage/emulated/0/Download/cpp_codebases/llvm/clang/include/clang/Analysis/PathDiagnostic.h",
  "source_line": 61,
  "validation_status": "validated"
}