{
  "code": "#include <cstddef>\n#include <cstdint>\n#include <limits>\n#include \"absl/base/attributes.h\"\n#include \"absl/base/casts.h\"\n#include \"absl/base/config.h\"\n#include \"absl/strings/string_view.h\"\n#include \"absl/types/span.h\"\n\nusing namespace absl;\nusing namespace log_internal;\n\nextern \"C\" {\n\nvoid BLOCK-CPP-05772_execute() {\n    { return 0; }\n}\n\n} // extern \"C\"\n",
  "id": "BLOCK-CPP-05772",
  "language": "c++",
  "source_file": "/storage/emulated/0/Download/cpp_codebases/abseil/absl/log/internal/proto.h",
  "source_line": 210,
  "validation_status": "validated"
}