{
  "code": "#include \"clang/AST/Decl.h\"\n#include \"clang/AST/Stmt.h\"\n\nusing namespace clang;\n\nextern \"C\" {\n\nvoid BLOCK-CPP-21867_execute() {\n    {\n\nusing DefMapTy = llvm::DenseMap<const VarDecl *, std::vector<const VarDecl *>>;\n\n/// The interface that lets the caller handle unsafe buffer usage analysis\n/// results by overriding this class's handle... methods.\nclass UnsafeBufferUsageHandler {\npublic:\n  UnsafeBufferUsageHandler() = default;\n  virtual ~UnsafeBufferUsageHandler() = default;\n\n  /// This analyses produces large fixits that are organized into lists\n  /// of primitive fixits (individual insertions/removals/replacements).\n  using FixItList = llvm::SmallVectorImpl<FixItHint>;\n\n  /// Invoked when an unsafe operation over raw pointers is found.\n  virtual void handleUnsafeOperation(const Stmt *Operation,\n                                     bool IsRelatedToDecl) = 0;\n\n  /// Invoked when a fix is suggested against a variable. This function groups\n  /// all variables that must be fixed together (i.e their types must be changed to the\n  /// same target type to prevent type mismatches) into a single fixit.\n  virtual void handleUnsafeVariableGroup(const VarDecl *Variable,\n                                         const DefMapTy &VarGrpMap,\n                                         FixItList &&Fixes) = 0;\n\n  /// Returns a reference to the `Preprocessor`:\n  virtual bool isSafeBufferOptOut(const SourceLocation &Loc) const = 0;\n\n  virtual std::string\n  getUnsafeBufferUsageAttributeTextAt(SourceLocation Loc,\n                                      StringRef WSSuffix = \"\") const = 0;\n};\n\n// This function invokes the analysis and allows the caller to react to it\n// through the handler class.\nvoid checkUnsafeBufferUsage(const Decl *D, UnsafeBufferUsageHandler &Handler,\n                            bool EmitSuggestions);\n\nnamespace internal {\n// Tests if any two `FixItHint`s in `FixIts` conflict.  Two `FixItHint`s\n// conflict if they have overlapping source ranges.\nbool anyConflict(const llvm::SmallVectorImpl<FixItHint> &FixIts,\n                 const SourceManager &SM);\n} // namespace internal\n}\n}\n\n} // extern \"C\"\n",
  "id": "BLOCK-CPP-21867",
  "language": "c++",
  "source_file": "/storage/emulated/0/Download/cpp_codebases/llvm/clang/include/clang/Analysis/Analyses/UnsafeBufferUsage.h",
  "source_line": 20,
  "validation_status": "validated"
}