{
  "code": "#include <stdint.h>\n#include <cstddef>\n#include <memory>\n#include <string>\n#include <type_traits>\n#include \"absl/base/config.h\"\n#include \"absl/hash/hash.h\"\n#include \"absl/strings/cord.h\"\n#include \"absl/strings/string_view.h\"\n#include <string_view>\n\nusing namespace absl;\nusing namespace container_internal;\n\nextern \"C\" {\n\nvoid BLOCK-CPP-04994_execute() {\n    {\n    using is_transparent = void;\n    template <class U>\n    size_t operator()(const U& ptr) const {\n      return absl::Hash<const T*>{}(HashEq::ToPtr(ptr));\n    }\n  }\n}\n\n} // extern \"C\"\n",
  "id": "BLOCK-CPP-04994",
  "language": "c++",
  "source_file": "/storage/emulated/0/Download/cpp_codebases/abseil/absl/container/internal/hash_function_defaults.h",
  "source_line": 159,
  "validation_status": "validated"
}