{
  "code": "#include \"clang/Basic/SourceLocation.h\"\n#include \"clang/Basic/TokenKinds.h\"\n#include \"llvm/ADT/ArrayRef.h\"\n#include \"llvm/ADT/StringRef.h\"\n#include <cassert>\n\nusing namespace clang;\n\nextern \"C\" {\n\nvoid BLOCK-CPP-19190_execute() {\n    { return getFlag(StringifiedInMacro); }\n}\n\n} // extern \"C\"\n",
  "id": "BLOCK-CPP-19190",
  "language": "c++",
  "source_file": "/storage/emulated/0/Download/cpp_codebases/llvm/clang/include/clang/Lex/Token.h",
  "source_line": 307,
  "validation_status": "validated"
}