{
  "code": "#include \"clang/Basic/AttrSubjectMatchRules.h\"\n#include \"clang/Basic/AttributeCommonInfo.h\"\n#include \"llvm/ADT/ArrayRef.h\"\n#include \"llvm/Support/Registry.h\"\n#include <climits>\n#include <list>\n\nusing namespace clang;\n\nextern \"C\" {\n\nvoid BLOCK-CPP-16714_execute() {\n    {\n  /// Corresponds to the Kind enum.\n  unsigned AttrKind : 16;\n  /// The number of required arguments of this attribute.\n  unsigned NumArgs : 4;\n  /// The number of optional arguments of this attributes.\n  unsigned OptArgs : 4;\n  /// The number of non-fake arguments specified in the attribute definition.\n  unsigned NumArgMembers : 4;\n  /// True if the parsing does not match the semantic content.\n  unsigned HasCustomParsing : 1;\n  // True if this attribute accepts expression parameter pack expansions.\n  unsigned AcceptsExprPack : 1;\n  /// True if this attribute is only available for certain targets.\n  unsigned IsTargetSpecific : 1;\n  /// True if this attribute applies to types.\n  unsigned IsType : 1;\n  /// True if this attribute applies to statements.\n  unsigned IsStmt : 1;\n  /// True if this attribute has any spellings that are known to gcc.\n  unsigned IsKnownToGCC : 1;\n  /// True if this attribute is supported by #pragma clang attribute.\n  unsigned IsSupportedByPragmaAttribute : 1;\n  /// The syntaxes supported by this attribute and how they're spelled.\n  struct Spelling {\n    AttributeCommonInfo::Syntax Syntax;\n    const char *NormalizedFullName;\n  };\n  ArrayRef<Spelling> Spellings;\n  // The names of the known arguments of this attribute.\n  ArrayRef<const char *> ArgNames;\n\nprotected:\n  constexpr ParsedAttrInfo(AttributeCommonInfo::Kind AttrKind =\n                               AttributeCommonInfo::NoSemaHandlerAttribute)\n      : AttrKind(AttrKind), NumArgs(0), OptArgs(0), NumArgMembers(0),\n        HasCustomParsing(0), AcceptsExprPack(0), IsTargetSpecific(0), IsType(0),\n        IsStmt(0), IsKnownToGCC(0), IsSupportedByPragmaAttribute(0) {}\n\n  constexpr ParsedAttrInfo(AttributeCommonInfo::Kind AttrKind, unsigned NumArgs,\n                           unsigned OptArgs, unsigned NumArgMembers,\n                           unsigned HasCustomParsing, unsigned AcceptsExprPack,\n                           unsigned IsTargetSpecific, unsigned IsType,\n                           unsigned IsStmt, unsigned IsKnownToGCC,\n                           unsigned IsSupportedByPragmaAttribute,\n                           ArrayRef<Spelling> Spellings,\n                           ArrayRef<const char *> ArgNames)\n      : AttrKind(AttrKind), NumArgs(NumArgs), OptArgs(OptArgs),\n        NumArgMembers(NumArgMembers), HasCustomParsing(HasCustomParsing),\n        AcceptsExprPack(AcceptsExprPack), IsTargetSpecific(IsTargetSpecific),\n        IsType(IsType), IsStmt(IsStmt), IsKnownToGCC(IsKnownToGCC),\n        IsSupportedByPragmaAttribute(IsSupportedByPragmaAttribute),\n        Spellings(Spellings), ArgNames(ArgNames) {}\n\npublic:\n  virtual ~ParsedAttrInfo() = default;\n\n  /// Check if this attribute has specified spelling.\n  bool hasSpelling(AttributeCommonInfo::Syntax Syntax, StringRef Name) const {\n    return llvm::any_of(Spellings, [&](const Spelling &S) {\n      return (S.Syntax == Syntax && S.NormalizedFullName == Name);\n    });\n  }\n\n  /// Check if this attribute appertains to D, and issue a diagnostic if not.\n  virtual bool diagAppertainsToDecl(Sema &S, const ParsedAttr &Attr,\n                                    const Decl *D) const {\n    return true;\n  }\n  /// Check if this attribute appertains to St, and issue a diagnostic if not.\n  virtual bool diagAppertainsToStmt(Sema &S, const ParsedAttr &Attr,\n                                    const Stmt *St) const {\n    return true;\n  }\n  /// Check if the given attribute is mutually exclusive with other attributes\n  /// already applied to the given declaration.\n  virtual bool diagMutualExclusion(Sema &S, const ParsedAttr &A,\n                                   const Decl *D) const {\n    return true;\n  }\n  /// Check if this attribute is allowed by the language we are compiling.\n  virtual bool acceptsLangOpts(const LangOptions &LO) const { return true; }\n\n  /// Check if this attribute is allowed when compiling for the given target.\n  virtual bool existsInTarget(const TargetInfo &Target) const { return true; }\n  /// Convert the spelling index of Attr to a semantic spelling enum value.\n  virtual unsigned\n  spellingIndexToSemanticSpelling(const ParsedAttr &Attr) const {\n    return UINT_MAX;\n  }\n  /// Returns true if the specified parameter index for this attribute in\n  /// Attr.td is an ExprArgument or VariadicExprArgument, or a subclass thereof;\n  /// returns false otherwise.\n  virtual bool isParamExpr(size_t N) const { return false; }\n  /// Populate Rules with the match rules of this attribute.\n  virtual void getPragmaAttributeMatchRules(\n      llvm::SmallVectorImpl<std::pair<attr::SubjectMatchRule, bool>> &Rules,\n      const LangOptions &LangOpts) const {}\n\n  enum AttrHandling { NotHandled, AttributeApplied, AttributeNotApplied };\n  /// If this ParsedAttrInfo knows how to handle this ParsedAttr applied to this\n  /// Decl then do so and return either AttributeApplied if it was applied or\n  /// AttributeNotApplied if it wasn't. Otherwise return NotHandled.\n  virtual AttrHandling handleDeclAttribute(Sema &S, Decl *D,\n                                           const ParsedAttr &Attr) const {\n    return NotHandled;\n  }\n\n  static const ParsedAttrInfo &get(const AttributeCommonInfo &A);\n  static ArrayRef<const ParsedAttrInfo *> getAllBuiltin();\n}\n}\n\n} // extern \"C\"\n",
  "id": "BLOCK-CPP-16714",
  "language": "c++",
  "source_file": "/storage/emulated/0/Download/cpp_codebases/llvm/clang/include/clang/Basic/ParsedAttrInfo.h",
  "source_line": 34,
  "validation_status": "validated"
}